api_gerenciador/__init__.py
api_gerenciador/package.py
api_gerenciador/utils.py
api_gerenciador-0.24.0.dist-info/METADATA
api_gerenciador-0.24.0.dist-info/WHEEL
api_gerenciador-0.24.0.dist-info/top_level.txt
api_gerenciador-0.24.0.dist-info/RECORD
