Metadata-Version: 2.1
Name: api_gerenciador
Version: 0.24.0
Summary: Biblioteca que executa ações de uma API
Author: Rafael Gomes de Oliveira
Author-email: rafaelprotest4@gmail.com
Requires-Dist: python-dotenv
